{
	"orð": "fułlraða",
	"flokkur": "sagnorð",
	"samsett": [
		{
			"mynd": "fułl",
			"samsetning": "stofn",
			"kennistrengur": "smáo.ao-fułl"
		},
		{
			"kennistrengur": "so-raða"
		}
	],
	"germynd": {
		"nafnháttur": "fułlraða",
		"sagnbót": "fułlraðað",
		"boðháttur": {
			"stýfður": "fułlraða",
			"et": "fułlraðaðu",
			"ft": "fułlraðið"
		},
		"persónuleg": {
			"framsöguháttur": {
				"nútíð": {
					"et": ["fułlraða", "fułlraðar", "fułlraðar"],
					"ft": ["fułlröðum", "fułlraðið", "fułlraða"]
				},
				"þátíð": {
					"et": ["fułlraðaði", "fułlraðaðir", "fułlraðaði"],
					"ft": ["fułlröðuðum", "fułlröðuðuð", "fułlröðuðu"]
				}
			},
			"viðtengingarháttur": {
				"nútíð": {
					"et": ["fułlraði", "fułlraðir", "fułlraði"],
					"ft": ["fułlröðum", "fułlraðið", "fułlraði"]
				},
				"þátíð": {
					"et": ["fułlraðaði", "fułlraðaðir", "fułlraðaði"],
					"ft": ["fułlröðuðum", "fułlröðuðuð", "fułlröðuðu"]
				}
			}
		},
		"spurnarmyndir": {
			"framsöguháttur": {
				"nútíð": {
					"et": "fułlraðarðu",
					"ft": "fułlraðiði"
				},
				"þátíð": {
					"et": "fułlraðaðirðu",
					"ft": "fułlröðuðuði"
				}
			},
			"viðtengingarháttur": {
				"nútíð": {
					"et": "fułlraðirðu",
					"ft": "fułlraðiði"
				},
				"þátíð": {
					"et": "fułlraðaðirðu",
					"ft": "fułlröðuðuði"
				}
			}
		}
	},
	"miðmynd": {
		"nafnháttur": "fułlraðast",
		"sagnbót": "fułlraðast",
		"persónuleg": {
			"framsöguháttur": {
				"nútíð": {
					"et": ["fułlraðast", "fułlraðast", "fułlraðast"],
					"ft": ["fułlröðumst", "fułlraðist", "fułlraðast"]
				},
				"þátíð": {
					"et": ["fułlraðaðist", "fułlraðaðist", "fułlraðaðist"],
					"ft": ["fułlröðuðumst", "fułlröðuðust", "fułlröðuðust"]
				}
			},
			"viðtengingarháttur": {
				"nútíð": {
					"et": ["fułlraðist", "fułlraðist", "fułlraðist"],
					"ft": ["fułlröðumst", "fułlraðist", "fułlraðist"]
				},
				"þátíð": {
					"et": ["fułlraðaðist", "fułlraðaðist", "fułlraðaðist"],
					"ft": ["fułlröðuðumst", "fułlröðuðust", "fułlröðuðust"]
				}
			}
		},
		"spurnarmyndir": {
			"framsöguháttur": {
				"nútíð": {
					"et": "fułlraðastu"
				},
				"þátíð": {
					"et": "fułlraðaðistu"
				}
			},
			"viðtengingarháttur": {
				"nútíð": {
					"et": "fułlraðistu"
				},
				"þátíð": {
					"et": "fułlraðaðistu"
				}
			}
		}
	},
	"lýsingarháttur": {
		"nútíðar": "fułlraðandi",
		"þátíðar": {
			"sb": {
				"et": {
					"kk": ["fułlraðaður", "fułlraðaðan", "fułlröðuðum", "fułlraðaðs"],
					"kvk": ["fułlröðuð", "fułlraðaða", "fułlraðaðri", "fułlraðaðrar"],
					"hk": ["fułlraðað", "fułlraðað", "fułlröðuðu", "fułlraðaðs"]
				},
				"ft": {
					"kk": ["fułlraðaðir", "fułlraðaða", "fułlröðuðum", "fułlraðaðra"],
					"kvk": ["fułlraðaðar", "fułlraðaðar", "fułlröðuðum", "fułlraðaðra"],
					"hk": ["fułlröðuð", "fułlröðuð", "fułlröðuðum", "fułlraðaðra"]
				}
			},
			"vb": {
				"et": {
					"kk": ["fułlraðaði", "fułlraðaða", "fułlraðaða", "fułlraðaða"],
					"kvk": ["fułlraðaða", "fułlröðuðu", "fułlröðuðu", "fułlröðuðu"],
					"hk": ["fułlraðaða", "fułlraðaða", "fułlraðaða", "fułlraðaða"]
				},
				"ft": {
					"kk": ["fułlröðuðu", "fułlröðuðu", "fułlröðuðu", "fułlröðuðu"],
					"kvk": ["fułlröðuðu", "fułlröðuðu", "fułlröðuðu", "fułlröðuðu"],
					"hk": ["fułlröðuðu", "fułlröðuðu", "fułlröðuðu", "fułlröðuðu"]
				}
			}
		}
	},
	"kennistrengur": "so-fułlraða",
	"hash": "1cdfb23e7e8b0d34af6881a3b92b1234e5e89d2ec980eae7acc2367948cf7eba"
}