{
	"orð": "Alexubarn",
	"flokkur": "nafnorð",
	"kyn": "hk",
	"samsett": [
		{
			"mynd": "Alexu",
			"samsetning": "eignarfalls",
			"kennistrengur": "sérn.en-Alexa-kvk"
		},
		{
			"kennistrengur": "no-barn-hk"
		}
	],
	"et": {
		"ág": ["Alexubarn", "Alexubarn", "Alexubarni", "Alexubarns"],
		"mg": ["Alexubarnið", "Alexubarnið", "Alexubarninu", "Alexubarnsins"]
	},
	"ft": {
		"ág": ["Alexubörn", "Alexubörn", "Alexubörnum", "Alexubarna"],
		"mg": ["Alexubörnin", "Alexubörnin", "Alexubörnunum", "Alexubarnanna"]
	},
	"kennistrengur": "no-Alexubarn-hk",
	"hash": "34d20b0d9704b3ce957b891df752ae673e2ef164593dc68a401064c9c7468f8d"
}