{
	"orð": "biskupstíð",
	"flokkur": "nafnorð",
	"kyn": "kvk",
	"samsett": [
		{
			"mynd": "biskups",
			"samsetning": "eignarfalls",
			"kennistrengur": "no-biskup-kk"
		},
		{
			"beygingar": ["et"],
			"kennistrengur": "no-tíð-kvk"
		}
	],
	"et": {
		"ág": ["biskupstíð", "biskupstíð", "biskupstíð", "biskupstíðar"],
		"mg": ["biskupstíðin", "biskupstíðina", "biskupstíðinni", "biskupstíðarinnar"]
	},
	"kennistrengur": "no-biskupstíð-kvk",
	"hash": "3cf4a247b274d9d94225c01325b772723ec06a8c8623e1615b3a1f9da6623789"
}