{
	"orð": "eigendahópur",
	"flokkur": "nafnorð",
	"kyn": "kk",
	"samsett": [
		{
			"mynd": "eigenda",
			"samsetning": "eignarfalls",
			"kennistrengur": "no-eigandi-kk"
		},
		{
			"kennistrengur": "no-hópur-kk"
		}
	],
	"et": {
		"ág": ["eigendahópur", "eigendahóp", "eigendahóp", "eigendahóps"],
		"mg": ["eigendahópurinn", "eigendahópinn", "eigendahópnum", "eigendahópsins"]
	},
	"ft": {
		"ág": ["eigendahópar", "eigendahópa", "eigendahópum", "eigendahópa"],
		"mg": ["eigendahóparnir", "eigendahópana", "eigendahópunum", "eigendahópanna"]
	},
	"kennistrengur": "no-eigendahópur-kk",
	"hash": "2bf5fbe7f8d14d13c621d4435e347f4c594d018fcc569e74331a3fe00b4e4b1f"
}