{
	"orð": "eiginþyngd",
	"flokkur": "nafnorð",
	"kyn": "kvk",
	"samsett": [
		{
			"mynd": "eigin",
			"samsetning": "stofn",
			"kennistrengur": "fn.óákv-eiginn"
		},
		{
			"beygingar": ["et"],
			"kennistrengur": "no-þyngd-kvk"
		}
	],
	"et": {
		"ág": ["eiginþyngd", "eiginþyngd", "eiginþyngd", "eiginþyngdar"],
		"mg": ["eiginþyngdin", "eiginþyngdina", "eiginþyngdinni", "eiginþyngdarinnar"]
	},
	"kennistrengur": "no-eiginþyngd-kvk",
	"hash": "33b308017b3e2914ed50a2fe523bb58ea38c91c3dec48eb71acfaab7e792cf97"
}