{
	"orð": "forsetaefni",
	"flokkur": "nafnorð",
	"kyn": "hk",
	"samsett": [
		{
			"mynd": "for",
			"samsetning": "stofn",
			"kennistrengur": "smáo.ao-for-ó"
		},
		{
			"mynd": "seta",
			"samsetning": "eignarfalls",
			"kennistrengur": "no-seti-kk"
		},
		{
			"kennistrengur": "no-efni-hk"
		}
	],
	"et": {
		"ág": ["forsetaefni", "forsetaefni", "forsetaefni", "forsetaefnis"],
		"mg": ["forsetaefnið", "forsetaefnið", "forsetaefninu", "forsetaefnisins"]
	},
	"ft": {
		"ág": ["forsetaefni", "forsetaefni", "forsetaefnum", "forsetaefna"],
		"mg": ["forsetaefnin", "forsetaefnin", "forsetaefnunum", "forsetaefnanna"]
	},
	"kennistrengur": "no-forsetaefni-hk",
	"hash": "fd0345e888e88cfd964f1420db91a9fadbc22e7e1e84dcdaee9ef0fe2536510d"
}