{
	"orð": "framsal",
	"flokkur": "nafnorð",
	"kyn": "hk",
	"samsett": [
		{
			"mynd": "fram",
			"samsetning": "stofn",
			"kennistrengur": "smáo.fs-fram"
		},
		{
			"kennistrengur": "no-sal-hk"
		}
	],
	"et": {
		"ág": ["framsal", "framsal", "framsali", "framsals"],
		"mg": ["framsalið", "framsalið", "framsalinu", "framsalsins"]
	},
	"ft": {
		"ág": ["framsöl", "framsöl", "framsölum", "framsala"],
		"mg": ["framsölin", "framsölin", "framsölunum", "framsalanna"]
	},
	"kennistrengur": "no-framsal-hk",
	"hash": "34080b27b863d3ca98cd991e503d925977d38c396f22e95b03e6b636ffd2babe"
}