{
	"orð": "Freysbarn",
	"flokkur": "nafnorð",
	"kyn": "hk",
	"merking": "Frey",
	"samsett": [
		{
			"mynd": "Freys",
			"samsetning": "eignarfalls",
			"kennistrengur": "sérn.en-Frey-hk"
		},
		{
			"kennistrengur": "no-barn-hk"
		}
	],
	"et": {
		"ág": ["Freysbarn", "Freysbarn", "Freysbarni", "Freysbarns"],
		"mg": ["Freysbarnið", "Freysbarnið", "Freysbarninu", "Freysbarnsins"]
	},
	"ft": {
		"ág": ["Freysbörn", "Freysbörn", "Freysbörnum", "Freysbarna"],
		"mg": ["Freysbörnin", "Freysbörnin", "Freysbörnunum", "Freysbarnanna"]
	},
	"kennistrengur": "no-Freysbarn-hk-_Frey_",
	"hash": "3eee6b4c723bb7311c05ef21b3302b3e11ac161f073283bca30bfc25f3c79896"
}