{
	"orð": "frumvarp",
	"flokkur": "nafnorð",
	"kyn": "hk",
	"samsett": [
		{
			"mynd": "frum",
			"samsetning": "stofn",
			"kennistrengur": "no-frum-hk"
		},
		{
			"kennistrengur": "no-varp-hk"
		}
	],
	"et": {
		"ág": ["frumvarp", "frumvarp", "frumvarpi", "frumvarps"],
		"mg": ["frumvarpið", "frumvarpið", "frumvarpinu", "frumvarpsins"]
	},
	"ft": {
		"ág": ["frumvörp", "frumvörp", "frumvörpum", "frumvarpa"],
		"mg": ["frumvörpin", "frumvörpin", "frumvörpunum", "frumvarpanna"]
	},
	"kennistrengur": "no-frumvarp-hk",
	"hash": "3acfcd3941d04e95a762705755a5c2ebffe1e0cb3cabb253d374fbeffd6d91df"
}