{
	"orð": "félagssamningur",
	"flokkur": "nafnorð",
	"kyn": "kk",
	"samsett": [
		{
			"mynd": "félags",
			"samsetning": "eignarfalls",
			"kennistrengur": "no-félag-hk"
		},
		{
			"kennistrengur": "no-samningur-kk"
		}
	],
	"et": {
		"ág": ["félagssamningur", "félagssamning", "félagssamningi", "félagssamnings"],
		"mg": ["félagssamningurinn", "félagssamninginn", "félagssamningnum", "félagssamningsins"]
	},
	"ft": {
		"ág": ["félagssamningar", "félagssamninga", "félagssamningum", "félagssamninga"],
		"mg": ["félagssamningarnir", "félagssamningana", "félagssamningunum", "félagssamninganna"]
	},
	"kennistrengur": "no-félagssamningur-kk",
	"hash": "63b3d68e1c77fb86cc03defbcf8d6a88330a72bf8eb9cff851cfa6a61f69157e"
}