{
	"orð": "greiðslumiðlunarstarfsemi",
	"flokkur": "nafnorð",
	"kyn": "kvk",
	"samsett": [
		{
			"mynd": "greiðslumiðlunar",
			"samsetning": "eignarfalls",
			"kennistrengur": "no-greiðslumiðlun-kvk"
		},
		{
			"kennistrengur": "no-starfsemi-kvk"
		}
	],
	"et": {
		"ág": ["greiðslumiðlunarstarfsemi", "greiðslumiðlunarstarfsemi", "greiðslumiðlunarstarfsemi", "greiðslumiðlunarstarfsemi"],
		"mg": ["greiðslumiðlunarstarfsemin", "greiðslumiðlunarstarfsemina", "greiðslumiðlunarstarfseminni", "greiðslumiðlunarstarfseminnar"]
	},
	"kennistrengur": "no-greiðslumiðlunarstarfsemi-kvk",
	"hash": "dfe76b6312c21140c51c0757ec3a9801be66f04c177c541c7a593de8737589bb"
}