{
	"orð": "heimaríki",
	"flokkur": "nafnorð",
	"kyn": "hk",
	"samsett": [
		{
			"mynd": "heima",
			"samsetning": "stofn",
			"kennistrengur": "smáo.ao-heima"
		},
		{
			"kennistrengur": "no-ríki-hk"
		}
	],
	"et": {
		"ág": ["heimaríki", "heimaríki", "heimaríki", "heimaríkis"],
		"mg": ["heimaríkið", "heimaríkið", "heimaríkinu", "heimaríkisins"]
	},
	"ft": {
		"ág": ["heimaríki", "heimaríki", "heimaríkjum", "heimaríkja"],
		"mg": ["heimaríkin", "heimaríkin", "heimaríkjunum", "heimaríkjanna"]
	},
	"kennistrengur": "no-heimaríki-hk",
	"hash": "4ba778a3e43a92219219daeac9bfbca3ad1b3ea4e6e13686e9a7477f583f7dff"
}