{
	"orð": "heimilisnotandi",
	"flokkur": "nafnorð",
	"kyn": "kk",
	"samsett": [
		{
			"mynd": "heimilis",
			"samsetning": "eignarfalls",
			"kennistrengur": "no-heimili-hk"
		},
		{
			"kennistrengur": "no-notandi-kk"
		}
	],
	"et": {
		"ág": ["heimilisnotandi", "heimilisnotanda", "heimilisnotanda", "heimilisnotanda"],
		"mg": ["heimilisnotandinn", "heimilisnotandann", "heimilisnotandanum", "heimilisnotandans"]
	},
	"ft": {
		"ág": ["heimilisnotendur", "heimilisnotendur", "heimilisnotendum", "heimilisnotenda"],
		"mg": ["heimilisnotendurnir", "heimilisnotendurna", "heimilisnotendunum", "heimilisnotendanna"]
	},
	"kennistrengur": "no-heimilisnotandi-kk",
	"hash": "55646968b91450b44a54086e89b7ce890da9c59e29cb6cce5038a30959be1eee"
}