{
	"orð": "hlutfałl",
	"flokkur": "nafnorð",
	"kyn": "hk",
	"samsett": [
		{
			"mynd": "hlut",
			"samsetning": "stofn",
			"kennistrengur": "no-hlutur-kk"
		},
		{
			"kennistrengur": "no-fałl-hk"
		}
	],
	"et": {
		"ág": ["hlutfałl", "hlutfałl", "hlutfałli", "hlutfalls"],
		"mg": ["hlutfałlið", "hlutfałlið", "hlutfałlinu", "hlutfałlsins"]
	},
	"ft": {
		"ág": ["hlutföłl", "hlutföłl", "hlutföłlum", "hlutfałla"],
		"mg": ["hlutföłlin", "hlutföłlin", "hlutföłlunum", "hlutfałlanna"]
	},
	"kennistrengur": "no-hlutfałl-hk",
	"hash": "01b4c9980c9bd9fc1ad2e96f0bb1789bacf238ed58ca4c97f2ee84bd1f4f18c0"
}