{
	"orð": "húsbílaeigandi",
	"flokkur": "nafnorð",
	"kyn": "kk",
	"samsett": [
		{
			"mynd": "hús",
			"samsetning": "stofn",
			"kennistrengur": "no-hús-hk"
		},
		{
			"mynd": "bíla",
			"samsetning": "eignarfalls",
			"kennistrengur": "no-bíłl-kk"
		},
		{
			"kennistrengur": "no-eigandi-kk"
		}
	],
	"et": {
		"ág": ["húsbílaeigandi", "húsbílaeiganda", "húsbílaeiganda", "húsbílaeiganda"],
		"mg": ["húsbílaeigandinn", "húsbílaeigandann", "húsbílaeigandanum", "húsbílaeigandans"]
	},
	"ft": {
		"ág": ["húsbílaeigendur", "húsbílaeigendur", "húsbílaeigendum", "húsbílaeigenda"],
		"mg": ["húsbílaeigendurnir", "húsbílaeigendurna", "húsbílaeigendunum", "húsbílaeigendanna"]
	},
	"kennistrengur": "no-húsbílaeigandi-kk",
	"hash": "26288d393aa2735e74b033c5bc9fda5515d86e101d826f59a74b1e7df4c6c49e"
}