{
	"orð": "Jörgensbarn",
	"flokkur": "nafnorð",
	"kyn": "hk",
	"samsett": [
		{
			"mynd": "Jörgens",
			"samsetning": "eignarfalls",
			"kennistrengur": "sérn.en-Jörgen-kk"
		},
		{
			"kennistrengur": "no-barn-hk"
		}
	],
	"et": {
		"ág": ["Jörgensbarn", "Jörgensbarn", "Jörgensbarni", "Jörgensbarns"],
		"mg": ["Jörgensbarnið", "Jörgensbarnið", "Jörgensbarninu", "Jörgensbarnsins"]
	},
	"ft": {
		"ág": ["Jörgensbörn", "Jörgensbörn", "Jörgensbörnum", "Jörgensbarna"],
		"mg": ["Jörgensbörnin", "Jörgensbörnin", "Jörgensbörnunum", "Jörgensbarnanna"]
	},
	"kennistrengur": "no-Jörgensbarn-hk",
	"hash": "aaefb62f72c2a9b37c2f5e1bdacf6faca0c7ad1f94849526102fc9d90ed8b547"
}