{
	"orð": "kjölfestuverkefni",
	"flokkur": "nafnorð",
	"kyn": "hk",
	"samsett": [
		{
			"mynd": "kjölfestu",
			"samsetning": "eignarfalls",
			"kennistrengur": "no-kjölfesta-kvk"
		},
		{
			"kennistrengur": "no-verkefni-hk"
		}
	],
	"et": {
		"ág": ["kjölfestuverkefni", "kjölfestuverkefni", "kjölfestuverkefni", "kjölfestuverkefnis"],
		"mg": ["kjölfestuverkefnið", "kjölfestuverkefnið", "kjölfestuverkefninu", "kjölfestuverkefnisins"]
	},
	"ft": {
		"ág": ["kjölfestuverkefni", "kjölfestuverkefni", "kjölfestuverkefnum", "kjölfestuverkefna"],
		"mg": ["kjölfestuverkefnin", "kjölfestuverkefnin", "kjölfestuverkefnunum", "kjölfestuverkefnanna"]
	},
	"kennistrengur": "no-kjölfestuverkefni-hk",
	"hash": "9778cacd019889b7c55345cea68fff8cbb9153133c9006c854d96a9d409910ab"
}