{
	"orð": "klakleyfishafi",
	"flokkur": "nafnorð",
	"kyn": "kk",
	"samsett": [
		{
			"mynd": "klak",
			"samsetning": "stofn",
			"kennistrengur": "no-klak-hk"
		},
		{
			"mynd": "leyfis",
			"samsetning": "eignarfalls",
			"kennistrengur": "no-leyfi-hk"
		},
		{
			"kennistrengur": "no-hafi-kk-ó"
		}
	],
	"et": {
		"ág": ["klakleyfishafi", "klakleyfishafa", "klakleyfishafa", "klakleyfishafa"],
		"mg": ["klakleyfishafinn", "klakleyfishafann", "klakleyfishafanum", "klakleyfishafans"]
	},
	"ft": {
		"ág": ["klakleyfishafar", "klakleyfishafa", "klakleyfishöfum", "klakleyfishafa"],
		"mg": ["klakleyfishafarnir", "klakleyfishafana", "klakleyfishöfunum", "klakleyfishafanna"]
	},
	"kennistrengur": "no-klakleyfishafi-kk",
	"hash": "fda3fc54456b6b29eb7b5528ab5f04d25a62f8d2f9046bdb71447efa2e05dd09"
}