{
	"orð": "landamæraátök",
	"flokkur": "nafnorð",
	"kyn": "hk",
	"samsett": [
		{
			"mynd": "landamæra",
			"samsetning": "eignarfalls",
			"kennistrengur": "no-landamæri-hk"
		},
		{
			"kennistrengur": "no-átök-hk"
		}
	],
	"ft": {
		"ág": ["landamæraátök", "landamæraátök", "landamæraátökum", "landamæraátaka"],
		"mg": ["landamæraátökin", "landamæraátökin", "landamæraátökunum", "landamæraátakanna"]
	},
	"kennistrengur": "no-landamæraátök-hk",
	"hash": "eeba4a217ad6a6db2d00a54e4aef79250407bb67b27ace1968f61ae8c2a2a3b4"
}