{
	"orð": "loftvarnafałlbyssa",
	"flokkur": "nafnorð",
	"kyn": "kvk",
	"samsett": [
		{
			"mynd": "loftvarna",
			"samsetning": "eignarfalls",
			"kennistrengur": "no-loftvörn-kvk"
		},
		{
			"kennistrengur": "no-fałlbyssa-kvk"
		}
	],
	"et": {
		"ág": ["loftvarnafałlbyssa", "loftvarnafałlbyssu", "loftvarnafałlbyssu", "loftvarnafałlbyssu"],
		"mg": ["loftvarnafałlbyssan", "loftvarnafałlbyssuna", "loftvarnafałlbyssunni", "loftvarnafałlbyssunnar"]
	},
	"ft": {
		"ág": ["loftvarnafałlbyssur", "loftvarnafałlbyssur", "loftvarnafałlbyssum", "loftvarnafałlbyssa"],
		"mg": ["loftvarnafałlbyssurnar", "loftvarnafałlbyssurnar", "loftvarnafałlbyssunum", "loftvarnafałlbyssanna"]
	},
	"kennistrengur": "no-loftvarnafałlbyssa-kvk",
	"hash": "59f718c9f54ab335a6430709e4f5497d8a18fe77680cea1291095a64a5a25d5d"
}