{
	"orð": "lykilmælikvarði",
	"flokkur": "nafnorð",
	"kyn": "kk",
	"samsett": [
		{
			"mynd": "lykil",
			"samsetning": "stofn",
			"kennistrengur": "no-lykiłl-kk"
		},
		{
			"mynd": "mæli",
			"samsetning": "bandstafs",
			"kennistrengur": "so-mæla"
		},
		{
			"kennistrengur": "no-kvarði-kk"
		}
	],
	"et": {
		"ág": ["lykilmælikvarði", "lykilmælikvarða", "lykilmælikvarða", "lykilmælikvarða"],
		"mg": ["lykilmælikvarðinn", "lykilmælikvarðann", "lykilmælikvarðanum", "lykilmælikvarðans"]
	},
	"ft": {
		"ág": ["lykilmælikvarðar", "lykilmælikvarða", "lykilmælikvörðum", "lykilmælikvarða"],
		"mg": ["lykilmælikvarðarnir", "lykilmælikvarðana", "lykilmælikvörðunum", "lykilmælikvarðanna"]
	},
	"kennistrengur": "no-lykilmælikvarði-kk",
	"hash": "f4a56ad1c4497612c4698a1e902c648049bf3067307c61b6333242bc348ba488"
}