{
	"orð": "löggæslutilgangur",
	"flokkur": "nafnorð",
	"kyn": "kk",
	"samsett": [
		{
			"mynd": "lög",
			"samsetning": "stofn",
			"kennistrengur": "no-lög-hk"
		},
		{
			"mynd": "gæslu",
			"samsetning": "eignarfalls",
			"kennistrengur": "no-gæsla-kvk"
		},
		{
			"mynd": "til",
			"samsetning": "stofn",
			"kennistrengur": "smáo.fs-til"
		},
		{
			"beygingar": ["et"],
			"kennistrengur": "no-gangur-kk"
		}
	],
	"et": {
		"ág": ["löggæslutilgangur", "löggæslutilgang", "löggæslutilgangi", "löggæslutilgangs"],
		"mg": ["löggæslutilgangurinn", "löggæslutilganginn", "löggæslutilganginum", "löggæslutilgangsins"]
	},
	"kennistrengur": "no-löggæslutilgangur-kk",
	"hash": "18ed6bf788366b83f8052c68f6ff812dd26869da42da1d4b9218575779f427bf"
}