{
	"orð": "markmiðasetning",
	"flokkur": "nafnorð",
	"kyn": "kvk",
	"samsett": [
		{
			"mynd": "markmiða",
			"samsetning": "eignarfalls",
			"kennistrengur": "no-markmið-hk"
		},
		{
			"kennistrengur": "no-setning-kvk"
		}
	],
	"et": {
		"ág": ["markmiðasetning", "markmiðasetningu", "markmiðasetningu", "markmiðasetningar"],
		"mg": ["markmiðasetningin", "markmiðasetninguna", "markmiðasetningunni", "markmiðasetningarinnar"]
	},
	"ft": {
		"ág": ["markmiðasetningar", "markmiðasetningar", "markmiðasetningum", "markmiðasetninga"],
		"mg": ["markmiðasetningarnar", "markmiðasetningarnar", "markmiðasetningunum", "markmiðasetninganna"]
	},
	"kennistrengur": "no-markmiðasetning-kvk",
	"hash": "87e772f5117100ad736da437bc6b4fb5ca5bac3cc2a2c51d13b0248ac9552e49"
}