{
	"orð": "nýveiting",
	"flokkur": "nafnorð",
	"kyn": "kvk",
	"samsett": [
		{
			"mynd": "ný",
			"samsetning": "stofn",
			"kennistrengur": "lo-nýr"
		},
		{
			"kennistrengur": "no-veiting-kvk"
		}
	],
	"et": {
		"ág": ["nýveiting", "nýveitingu", "nýveitingu", "nýveitingar"],
		"mg": ["nýveitingin", "nýveitinguna", "nýveitingunni", "nýveitingarinnar"]
	},
	"ft": {
		"ág": ["nýveitingar", "nýveitingar", "nýveitingum", "nýveitinga"],
		"mg": ["nýveitingarnar", "nýveitingarnar", "nýveitingunum", "nýveitinganna"]
	},
	"kennistrengur": "no-nýveiting-kvk",
	"hash": "94ad4b27aa4cb1b386daa1e8453ba2faef367f4fe9d8dc3ae658f9af25aef368"
}