{
	"orð": "peningahítarverkefni",
	"flokkur": "nafnorð",
	"kyn": "hk",
	"samsett": [
		{
			"mynd": "peninga",
			"samsetning": "eignarfalls",
			"kennistrengur": "no-peningur-kk"
		},
		{
			"mynd": "hítar",
			"samsetning": "eignarfalls",
			"kennistrengur": "no-hít-kvk"
		},
		{
			"mynd": "verk",
			"samsetning": "stofn",
			"kennistrengur": "no-verk-hk"
		},
		{
			"kennistrengur": "no-efni-hk"
		}
	],
	"et": {
		"ág": ["peningahítarverkefni", "peningahítarverkefni", "peningahítarverkefni", "peningahítarverkefnis"],
		"mg": ["peningahítarverkefnið", "peningahítarverkefnið", "peningahítarverkefninu", "peningahítarverkefnisins"]
	},
	"ft": {
		"ág": ["peningahítarverkefni", "peningahítarverkefni", "peningahítarverkefnum", "peningahítarverkefna"],
		"mg": ["peningahítarverkefnin", "peningahítarverkefnin", "peningahítarverkefnunum", "peningahítarverkefnanna"]
	},
	"kennistrengur": "no-peningahítarverkefni-hk",
	"hash": "2447594a1a45623e0e6fe38ad975ef04842a693b362f68393df26036ea74a3b6"
}