{
	"orð": "samanburðarrannsókn",
	"flokkur": "nafnorð",
	"kyn": "kvk",
	"samsett": [
		{
			"mynd": "saman",
			"samsetning": "stofn",
			"kennistrengur": "smáo.ao-saman"
		},
		{
			"mynd": "burðar",
			"samsetning": "eignarfalls",
			"kennistrengur": "no-burður-kk"
		},
		{
			"mynd": "rann",
			"samsetning": "stofn",
			"kennistrengur": "no-rann-hk"
		},
		{
			"kennistrengur": "no-sókn-kvk"
		}
	],
	"et": {
		"ág": ["samanburðarrannsókn", "samanburðarrannsókn", "samanburðarrannsókn", "samanburðarrannsóknar"],
		"mg": ["samanburðarrannsóknin", "samanburðarrannsóknina", "samanburðarrannsókninni", "samanburðarrannsóknarinnar"]
	},
	"ft": {
		"ág": ["samanburðarrannsóknir", "samanburðarrannsóknir", "samanburðarrannsóknum", "samanburðarrannsókna"],
		"mg": ["samanburðarrannsóknirnar", "samanburðarrannsóknirnar", "samanburðarrannsóknunum", "samanburðarrannsóknanna"]
	},
	"kennistrengur": "no-samanburðarrannsókn-kvk",
	"hash": "010b60995a87b63a4e44978d8a69e361199490aa6d927e19ed47c33cecb7d4f9"
}