{
	"orð": "samræmismerking",
	"flokkur": "nafnorð",
	"kyn": "kvk",
	"samsett": [
		{
			"mynd": "samræmis",
			"samsetning": "eignarfalls",
			"kennistrengur": "no-samræmi-hk"
		},
		{
			"kennistrengur": "no-merking-kvk"
		}
	],
	"et": {
		"ág": ["samræmismerking", "samræmismerkingu", "samræmismerkingu", "samræmismerkingar"],
		"mg": ["samræmismerkingin", "samræmismerkinguna", "samræmismerkingunni", "samræmismerkingarinnar"]
	},
	"ft": {
		"ág": ["samræmismerkingar", "samræmismerkingar", "samræmismerkingum", "samræmismerkinga"],
		"mg": ["samræmismerkingarnar", "samræmismerkingarnar", "samræmismerkingunum", "samræmismerkinganna"]
	},
	"kennistrengur": "no-samræmismerking-kvk",
	"hash": "e7b7f9f403e2377a5c54e740027596f7b79ea9f7c9d3e69a8a16333dc66e9e28"
}