{
	"orð": "staðalaðferð",
	"flokkur": "nafnorð",
	"kyn": "kvk",
	"samsett": [
		{
			"mynd": "staðal",
			"samsetning": "stofn",
			"kennistrengur": "no-staðałl-kk"
		},
		{
			"mynd": "að",
			"samsetning": "stofn",
			"kennistrengur": "smáo.fs-að"
		},
		{
			"kennistrengur": "no-ferð-kvk"
		}
	],
	"et": {
		"ág": ["staðalaðferð", "staðalaðferð", "staðalaðferð", "staðalaðferðar"],
		"mg": ["staðalaðferðin", "staðalaðferðina", "staðalaðferðinni", "staðalaðferðarinnar"]
	},
	"ft": {
		"ág": ["staðalaðferðir", "staðalaðferðir", "staðalaðferðum", "staðalaðferða"],
		"mg": ["staðalaðferðirnar", "staðalaðferðirnar", "staðalaðferðunum", "staðalaðferðanna"]
	},
	"kennistrengur": "no-staðalaðferð-kvk",
	"hash": "187b9d4e053cf3816c4b6bc5dff04c95f038ff0d5f6147239b02a053040f59c3"
}