{
	"orð": "stjórnarerindi",
	"flokkur": "nafnorð",
	"kyn": "hk",
	"samsett": [
		{
			"mynd": "stjórnar",
			"samsetning": "eignarfalls",
			"kennistrengur": "no-stjórn-kvk"
		},
		{
			"kennistrengur": "no-erindi-hk"
		}
	],
	"et": {
		"ág": ["stjórnarerindi", "stjórnarerindi", "stjórnarerindi", "stjórnarerindis"],
		"mg": ["stjórnarerindið", "stjórnarerindið", "stjórnarerindinu", "stjórnarerindisins"]
	},
	"ft": {
		"ág": ["stjórnarerindi", "stjórnarerindi", "stjórnarerindum", "stjórnarerinda"],
		"mg": ["stjórnarerindin", "stjórnarerindin", "stjórnarerindunum", "stjórnarerindanna"]
	},
	"kennistrengur": "no-stjórnarerindi-hk",
	"hash": "31878d37a64fffb49201b2e8721bdb1e1805a8f8582b2cdf80a1adbaff51f4d7"
}