{
	"orð": "strætóbiðskýli",
	"flokkur": "nafnorð",
	"kyn": "hk",
	"samsett": [
		{
			"mynd": "strætó",
			"samsetning": "stofn",
			"kennistrengur": "no-strætó-kk"
		},
		{
			"kennistrengur": "no-biðskýli-hk"
		}
	],
	"et": {
		"ág": ["strætóbiðskýli", "strætóbiðskýli", "strætóbiðskýli", "strætóbiðskýlis"],
		"mg": ["strætóbiðskýlið", "strætóbiðskýlið", "strætóbiðskýlinu", "strætóbiðskýlisins"]
	},
	"ft": {
		"ág": ["strætóbiðskýli", "strætóbiðskýli", "strætóbiðskýlum", "strætóbiðskýla"],
		"mg": ["strætóbiðskýlin", "strætóbiðskýlin", "strætóbiðskýlunum", "strætóbiðskýlanna"]
	},
	"kennistrengur": "no-strætóbiðskýli-hk",
	"hash": "35b4002b0d93be88056569e2ed55752c7152534ac6516577bee805192dd65f42"
}