{
	"orð": "Styrkársbarn",
	"flokkur": "nafnorð",
	"kyn": "hk",
	"samsett": [
		{
			"mynd": "Styrkárs",
			"samsetning": "eignarfalls",
			"kennistrengur": "sérn.en-Styrkár-kk"
		},
		{
			"kennistrengur": "no-barn-hk"
		}
	],
	"et": {
		"ág": ["Styrkársbarn", "Styrkársbarn", "Styrkársbarni", "Styrkársbarns"],
		"mg": ["Styrkársbarnið", "Styrkársbarnið", "Styrkársbarninu", "Styrkársbarnsins"]
	},
	"ft": {
		"ág": ["Styrkársbörn", "Styrkársbörn", "Styrkársbörnum", "Styrkársbarna"],
		"mg": ["Styrkársbörnin", "Styrkársbörnin", "Styrkársbörnunum", "Styrkársbarnanna"]
	},
	"kennistrengur": "no-Styrkársbarn-hk",
	"hash": "b54adbf0e478e1b29220a2bf75f615d62a3c45cca81847f6284960184ded0e16"
}