{
	"orð": "sérfræðiþjónusta",
	"flokkur": "nafnorð",
	"kyn": "kvk",
	"samsett": [
		{
			"mynd": "sér",
			"samsetning": "stofn",
			"kennistrengur": "fn.a-sig"
		},
		{
			"mynd": "fræði",
			"samsetning": "stofn",
			"kennistrengur": "no-fræði-kvk"
		},
		{
			"kennistrengur": "no-þjónusta-kvk"
		}
	],
	"et": {
		"ág": ["sérfræðiþjónusta", "sérfræðiþjónustu", "sérfræðiþjónustu", "sérfræðiþjónustu"],
		"mg": ["sérfræðiþjónustan", "sérfræðiþjónustuna", "sérfræðiþjónustunni", "sérfræðiþjónustunnar"]
	},
	"ft": {
		"ág": ["sérfræðiþjónustur", "sérfræðiþjónustur", "sérfræðiþjónustum", "sérfræðiþjónustna"],
		"mg": ["sérfræðiþjónusturnar", "sérfræðiþjónusturnar", "sérfræðiþjónustunum", "sérfræðiþjónustnanna"]
	},
	"kennistrengur": "no-sérfræðiþjónusta-kvk",
	"hash": "8ecd0458e86754878102e4eeaab6e6b2a69398cd0d4ec1cc897f855872051565"
}