{
	"orð": "sérrefsilagaákvæði",
	"flokkur": "nafnorð",
	"kyn": "hk",
	"samsett": [
		{
			"mynd": "sér",
			"samsetning": "stofn",
			"kennistrengur": "fn.a-sig"
		},
		{
			"mynd": "refsi",
			"samsetning": "bandstafs",
			"kennistrengur": "so-refsa"
		},
		{
			"mynd": "laga",
			"samsetning": "eignarfalls",
			"kennistrengur": "no-lög-hk"
		},
		{
			"kennistrengur": "no-ákvæði-hk"
		}
	],
	"et": {
		"ág": ["sérrefsilagaákvæði", "sérrefsilagaákvæði", "sérrefsilagaákvæði", "sérrefsilagaákvæðis"],
		"mg": ["sérrefsilagaákvæðið", "sérrefsilagaákvæðið", "sérrefsilagaákvæðinu", "sérrefsilagaákvæðisins"]
	},
	"ft": {
		"ág": ["sérrefsilagaákvæði", "sérrefsilagaákvæði", "sérrefsilagaákvæðum", "sérrefsilagaákvæða"],
		"mg": ["sérrefsilagaákvæðin", "sérrefsilagaákvæðin", "sérrefsilagaákvæðunum", "sérrefsilagaákvæðanna"]
	},
	"kennistrengur": "no-sérrefsilagaákvæði-hk",
	"hash": "6f86557cd6210136e953ea266a2fe5989d3882d5708f623625894b39b9e4869b"
}