{
	"orð": "umhverfisvísindastofnun",
	"flokkur": "nafnorð",
	"kyn": "kvk",
	"samsett": [
		{
			"mynd": "umhverfis",
			"samsetning": "eignarfalls",
			"kennistrengur": "no-umhverfi-hk"
		},
		{
			"mynd": "vísinda",
			"samsetning": "eignarfalls",
			"kennistrengur": "no-vísindi-hk"
		},
		{
			"kennistrengur": "no-stofnun-kvk"
		}
	],
	"et": {
		"ág": ["umhverfisvísindastofnun", "umhverfisvísindastofnun", "umhverfisvísindastofnun", "umhverfisvísindastofnunar"],
		"mg": ["umhverfisvísindastofnunin", "umhverfisvísindastofnunina", "umhverfisvísindastofnuninni", "umhverfisvísindastofnunarinnar"]
	},
	"ft": {
		"ág": ["umhverfisvísindastofnanir", "umhverfisvísindastofnanir", "umhverfisvísindastofnunum", "umhverfisvísindastofnana"],
		"mg": ["umhverfisvísindastofnanirnar", "umhverfisvísindastofnanirnar", "umhverfisvísindastofnununum", "umhverfisvísindastofnananna"]
	},
	"kennistrengur": "no-umhverfisvísindastofnun-kvk",
	"hash": "d8f6a7272aa3a68f504f84ccb13759b8e79b38d6c9892dbac37ac61c91b953b0"
}