{
	"orð": "unglingur",
	"flokkur": "nafnorð",
	"kyn": "kk",
	"samsett": [
		{
			"mynd": "ung",
			"samsetning": "stofn",
			"kennistrengur": "lo-ungur"
		},
		{
			"kennistrengur": "no-lingur-kk"
		}
	],
	"et": {
		"ág": ["unglingur", "ungling", "unglingi", "unglings"],
		"mg": ["unglingurinn", "unglinginn", "unglingnum", "unglingsins"]
	},
	"ft": {
		"ág": ["unglingar", "unglinga", "unglingum", "unglinga"],
		"mg": ["unglingarnir", "unglingana", "unglingunum", "unglinganna"]
	},
	"kennistrengur": "no-unglingur-kk",
	"hash": "ed1563c08c75c870c0e7ac80900dfb38acdd6e34aa3248e53929d3ffe5f03595"
}