{
	"orð": "verðtrygging",
	"flokkur": "nafnorð",
	"kyn": "kvk",
	"samsett": [
		{
			"mynd": "verð",
			"samsetning": "stofn",
			"kennistrengur": "no-verð-hk"
		},
		{
			"mynd": "trygg",
			"samsetning": "stofn",
			"kennistrengur": "so-tryggja"
		},
		{
			"kennistrengur": "no-ing-kvk-ó"
		}
	],
	"et": {
		"ág": ["verðtrygging", "verðtryggingu", "verðtryggingu", "verðtryggingar"],
		"mg": ["verðtryggingin", "verðtrygginguna", "verðtryggingunni", "verðtryggingarinnar"]
	},
	"ft": {
		"ág": ["verðtryggingar", "verðtryggingar", "verðtryggingum", "verðtrygginga"],
		"mg": ["verðtryggingarnar", "verðtryggingarnar", "verðtryggingunum", "verðtrygginganna"]
	},
	"kennistrengur": "no-verðtrygging-kvk",
	"hash": "afdc933d04555193110f381aeb43e90f0fb66a2ad6377a453b4a80edd1578034"
}