{
	"orð": "verðleiki",
	"flokkur": "nafnorð",
	"kyn": "kk",
	"samsett": [
		{
			"mynd": "verð",
			"samsetning": "stofn",
			"kennistrengur": "no-verð-hk"
		},
		{
			"kennistrengur": "no-leiki-kk-ó"
		}
	],
	"et": {
		"ág": ["verðleiki", "verðleika", "verðleika", "verðleika"],
		"mg": ["verðleikinn", "verðleikann", "verðleikanum", "verðleikans"]
	},
	"ft": {
		"ág": ["verðleikar", "verðleika", "verðleikum", "verðleika"],
		"mg": ["verðleikarnir", "verðleikana", "verðleikunum", "verðleikanna"]
	},
	"kennistrengur": "no-verðleiki-kk",
	"hash": "69e2defdce208733f88e666f00de456ad17bf3d10babc0d8bd3c3c32badaa832"
}