{
	"orð": "Vövubarn",
	"flokkur": "nafnorð",
	"kyn": "hk",
	"samsett": [
		{
			"mynd": "Vövu",
			"samsetning": "eignarfalls",
			"kennistrengur": "sérn.en-Vava-kvk"
		},
		{
			"kennistrengur": "no-barn-hk"
		}
	],
	"et": {
		"ág": ["Vövubarn", "Vövubarn", "Vövubarni", "Vövubarns"],
		"mg": ["Vövubarnið", "Vövubarnið", "Vövubarninu", "Vövubarnsins"]
	},
	"ft": {
		"ág": ["Vövubörn", "Vövubörn", "Vövubörnum", "Vövubarna"],
		"mg": ["Vövubörnin", "Vövubörnin", "Vövubörnunum", "Vövubarnanna"]
	},
	"kennistrengur": "no-Vövubarn-hk",
	"hash": "273cd204081c329f7267226ec9c62cb9d9ab1b9365aa81a00f0ee46d978dfd33"
}