{
	"orð": "árangurshlutfałl",
	"flokkur": "nafnorð",
	"kyn": "hk",
	"samsett": [
		{
			"mynd": "árangurs",
			"samsetning": "eignarfalls",
			"kennistrengur": "no-árangur-kk"
		},
		{
			"mynd": "hlut",
			"samsetning": "stofn",
			"kennistrengur": "no-hlutur-kk"
		},
		{
			"kennistrengur": "no-fałl-hk"
		}
	],
	"et": {
		"ág": ["árangurshlutfałl", "árangurshlutfałl", "árangurshlutfałli", "árangurshlutfalls"],
		"mg": ["árangurshlutfałlið", "árangurshlutfałlið", "árangurshlutfałlinu", "árangurshlutfallsins"]
	},
	"ft": {
		"ág": ["árangurshlutföłl", "árangurshlutföłl", "árangurshlutföłlum", "árangurshlutfałla"],
		"mg": ["árangurshlutföłlin", "árangurshlutföłlin", "árangurshlutföłlunum", "árangurshlutfałlanna"]
	},
	"kennistrengur": "no-árangurshlutfałl-hk",
	"hash": "3cb421f94b4129792c1da586543173e11378a0915117819faa1bcebcd1175a11"
}