{
	"orð": "íbúðasvæði",
	"flokkur": "nafnorð",
	"kyn": "hk",
	"samsett": [
		{
			"mynd": "íbúða",
			"samsetning": "eignarfalls",
			"kennistrengur": "no-íbúð-kvk"
		},
		{
			"kennistrengur": "no-svæði-hk"
		}
	],
	"et": {
		"ág": ["íbúðasvæði", "íbúðasvæði", "íbúðasvæði", "íbúðasvæðis"],
		"mg": ["íbúðasvæðið", "íbúðasvæðið", "íbúðasvæðinu", "íbúðasvæðisins"]
	},
	"ft": {
		"ág": ["íbúðasvæði", "íbúðasvæði", "íbúðasvæðum", "íbúðasvæða"],
		"mg": ["íbúðasvæðin", "íbúðasvæðin", "íbúðasvæðunum", "íbúðasvæðanna"]
	},
	"kennistrengur": "no-íbúðasvæði-hk",
	"hash": "4f71ab5207832628f225cc57d420b11209fdf01f3f0a40ec5fee760b5cd58f71"
}