{
	"orð": "Fremri-Kárahnjúkar",
	"flokkur": "sérnafn",
	"undirflokkur": "örnefni",
	"kyn": "kk",
	"samsett": [
		{
			"myndir": "miðstig-vb-kk",
			"hástafa": true,
			"fylgir": "-",
			"kennistrengur": "lo-fremri"
		},
		{
			"kennistrengur": "sérn.ön-Kárahnjúkar-kk"
		}
	],
	"ft": {
		"ág": ["Fremri-Kárahnjúkar", "Fremri-Kárahnjúka", "Fremri-Kárahnjúkum", "Fremri-Kárahnjúka"]
	},
	"kennistrengur": "sérn.ön-Fremri-Kárahnjúkar-kk",
	"hash": "3f021190d6bcaeb381f962bbd103dab5f9901a197820d603da547b12f6038b49"
}