{
	"orð": "Kormlaðarson",
	"flokkur": "sérnafn",
	"undirflokkur": "kenninafn",
	"kyn": "kk",
	"samsett": [
		{
			"mynd": "Kormlaðar",
			"samsetning": "eignarfalls",
			"kennistrengur": "sérn.en-Kormlöð-kvk"
		},
		{
			"beygingar": ["et-ág", "ft-ág"],
			"kennistrengur": "no-son-kk"
		}
	],
	"et": {
		"ág": ["Kormlaðarson", "Kormlaðarson", "Kormlaðarsyni", "Kormlaðarsonar"]
	},
	"ft": {
		"ág": ["Kormlaðarsynir", "Kormlaðarsyni", "Kormlaðarsonum", "Kormlaðarsona"]
	},
	"kennistrengur": "sérn.kn-Kormlaðarson-kk",
	"hash": "ea357d7286e1908070b2d14bcb1ee5f71d9cc688f156ca86d4964a24220eb94f"
}