{
	"orð": "Lyngarsson",
	"flokkur": "sérnafn",
	"undirflokkur": "kenninafn",
	"kyn": "kk",
	"samsett": [
		{
			"mynd": "Lyngars",
			"samsetning": "eignarfalls",
			"kennistrengur": "sérn.en-Lyngar-kk"
		},
		{
			"beygingar": ["et-ág", "ft-ág"],
			"kennistrengur": "no-son-kk"
		}
	],
	"et": {
		"ág": ["Lyngarsson", "Lyngarsson", "Lyngarssyni", "Lyngarssonar"]
	},
	"ft": {
		"ág": ["Lyngarssynir", "Lyngarssyni", "Lyngarssonum", "Lyngarssona"]
	},
	"kennistrengur": "sérn.kn-Lyngarsson-kk",
	"hash": "e61ba87304c23ae531bf299e762c1f5d6de79d169d280db1c9694763d41f5435"
}