{
	"orð": "Mattíönuson",
	"flokkur": "sérnafn",
	"undirflokkur": "kenninafn",
	"kyn": "kk",
	"samsett": [
		{
			"mynd": "Mattíönu",
			"samsetning": "eignarfalls",
			"kennistrengur": "sérn.en-Mattíana-kvk"
		},
		{
			"beygingar": ["et-ág", "ft-ág"],
			"kennistrengur": "no-son-kk"
		}
	],
	"et": {
		"ág": ["Mattíönuson", "Mattíönuson", "Mattíönusyni", "Mattíönusonar"]
	},
	"ft": {
		"ág": ["Mattíönusynir", "Mattíönusyni", "Mattíönusonum", "Mattíönusona"]
	},
	"kennistrengur": "sérn.kn-Mattíönuson-kk",
	"hash": "4ca2d067eeafcc01c1a7fbe7667ba591e7c237f89b03d8e53bb9788ede19ff89"
}