{
	"orð": "Ugluspegilsson",
	"flokkur": "sérnafn",
	"undirflokkur": "kenninafn",
	"kyn": "kk",
	"samsett": [
		{
			"mynd": "Ugluspegils",
			"samsetning": "eignarfalls",
			"kennistrengur": "sérn.en-Ugluspegiłl-kk"
		},
		{
			"beygingar": ["et-ág", "ft-ág"],
			"kennistrengur": "no-son-kk"
		}
	],
	"et": {
		"ág": ["Ugluspegilsson", "Ugluspegilsson", "Ugluspegilssyni", "Ugluspegilssonar"]
	},
	"ft": {
		"ág": ["Ugluspegilssynir", "Ugluspegilssyni", "Ugluspegilssonum", "Ugluspegilssona"]
	},
	"kennistrengur": "sérn.kn-Ugluspegilsson-kk",
	"hash": "9a05ea4522ea09b70d33334de01e21077cd9b63ae8d618e36acfbfef96f0b655"
}