{
	"orð": "Vonarson",
	"flokkur": "sérnafn",
	"undirflokkur": "kenninafn",
	"kyn": "kk",
	"samsett": [
		{
			"mynd": "Vonar",
			"samsetning": "eignarfalls",
			"kennistrengur": "sérn.en-Von-kvk"
		},
		{
			"beygingar": ["et-ág", "ft-ág"],
			"kennistrengur": "no-son-kk"
		}
	],
	"et": {
		"ág": ["Vonarson", "Vonarson", "Vonarsyni", "Vonarsonar"]
	},
	"ft": {
		"ág": ["Vonarsynir", "Vonarsyni", "Vonarsonum", "Vonarsona"]
	},
	"kennistrengur": "sérn.kn-Vonarson-kk",
	"hash": "a1783a5b72ca2310b71436f5ccc8b9802ead3694349b60e4babbb57855a11174"
}