{
	"orð": "nýstofnaður",
	"flokkur": "lýsingarorð",
	"samsett": [
		{
			"mynd": "ný",
			"samsetning": "stofn",
			"kennistrengur": "lo-nýr"
		},
		{
			"kennistrengur": "lo-stofnaður"
		}
	],
	"frumstig": {
		"sb": {
			"et": {
				"kk": ["nýstofnaður", "nýstofnaðan", "nýstofnuðum", "nýstofnaðs"],
				"kvk": ["nýstofnuð", "nýstofnaða", "nýstofnaðri", "nýstofnaðrar"],
				"hk": ["nýstofnað", "nýstofnað", "nýstofnuðu", "nýstofnaðs"]
			},
			"ft": {
				"kk": ["nýstofnaðir", "nýstofnaða", "nýstofnuðum", "nýstofnaðra"],
				"kvk": ["nýstofnaðar", "nýstofnaðar", "nýstofnuðum", "nýstofnaðra"],
				"hk": ["nýstofnuð", "nýstofnuð", "nýstofnuðum", "nýstofnaðra"]
			}
		},
		"vb": {
			"et": {
				"kk": ["nýstofnaði", "nýstofnaða", "nýstofnaða", "nýstofnaða"],
				"kvk": ["nýstofnaða", "nýstofnuðu", "nýstofnuðu", "nýstofnuðu"],
				"hk": ["nýstofnaða", "nýstofnaða", "nýstofnaða", "nýstofnaða"]
			},
			"ft": {
				"kk": ["nýstofnuðu", "nýstofnuðu", "nýstofnuðu", "nýstofnuðu"],
				"kvk": ["nýstofnuðu", "nýstofnuðu", "nýstofnuðu", "nýstofnuðu"],
				"hk": ["nýstofnuðu", "nýstofnuðu", "nýstofnuðu", "nýstofnuðu"]
			}
		}
	},
	"kennistrengur": "lo-nýstofnaður",
	"hash": "c63a311d7a1874c3d5bb0829bc1ba1c7358b9ce20df60e6c315f578d024cbbde"
}