{
	"orð": "skráður",
	"flokkur": "lýsingarorð",
	"frumstig": {
		"sb": {
			"et": {
				"kk": ["skráður", "skráðan", "skráðum", "skráðs"],
				"kvk": ["skráð", "skráða", "skráðri", "skráðrar"],
				"hk": ["skráð", "skráð", "skráðu", "skráðs"]
			},
			"ft": {
				"kk": ["skráðir", "skráða", "skráðum", "skráðra"],
				"kvk": ["skráðar", "skráðar", "skráðum", "skráðra"],
				"hk": ["skráð", "skráð", "skráðum", "skráðra"]
			}
		},
		"vb": {
			"et": {
				"kk": ["skráði", "skráða", "skráða", "skráða"],
				"kvk": ["skráða", "skráðu", "skráðu", "skráðu"],
				"hk": ["skráða", "skráða", "skráða", "skráða"]
			},
			"ft": {
				"kk": ["skráðu", "skráðu", "skráðu", "skráðu"],
				"kvk": ["skráðu", "skráðu", "skráðu", "skráðu"],
				"hk": ["skráðu", "skráðu", "skráðu", "skráðu"]
			}
		}
	},
	"miðstig": {
		"vb": {
			"et": {
				"kk": ["skráðari", "skráðari", "skráðari", "skráðari"],
				"kvk": ["skráðari", "skráðari", "skráðari", "skráðari"],
				"hk": ["skráðara", "skráðara", "skráðara", "skráðara"]
			},
			"ft": {
				"kk": ["skráðari", "skráðari", "skráðari", "skráðari"],
				"kvk": ["skráðari", "skráðari", "skráðari", "skráðari"],
				"hk": ["skráðari", "skráðari", "skráðari", "skráðari"]
			}
		}
	},
	"efstastig": {
		"sb": {
			"et": {
				"kk": ["skráðastur", "skráðastan", "skráðustum", "skráðasts"],
				"kvk": ["skráðust", "skráðasta", "skráðastri", "skráðastrar"],
				"hk": ["skráðast", "skráðast", "skráðustu", "skráðasts"]
			},
			"ft": {
				"kk": ["skráðastir", "skráðasta", "skráðustum", "skráðastra"],
				"kvk": ["skráðastar", "skráðastar", "skráðustum", "skráðastra"],
				"hk": ["skráðust", "skráðust", "skráðustum", "skráðastra"]
			}
		},
		"vb": {
			"et": {
				"kk": ["skráðasti", "skráðasta", "skráðasta", "skráðasta"],
				"kvk": ["skráðasta", "skráðustu", "skráðustu", "skráðustu"],
				"hk": ["skráðasta", "skráðasta", "skráðasta", "skráðasta"]
			},
			"ft": {
				"kk": ["skráðustu", "skráðustu", "skráðustu", "skráðustu"],
				"kvk": ["skráðustu", "skráðustu", "skráðustu", "skráðustu"],
				"hk": ["skráðustu", "skráðustu", "skráðustu", "skráðustu"]
			}
		}
	},
	"kennistrengur": "lo-skráður",
	"hash": "2b3c047b829fa7e6e71c8c8a227ad99f6450b51b480d32882f323c67c32ee90d"
}