{
	"orð": "ólifaður",
	"flokkur": "lýsingarorð",
	"samsett": [
		{
			"mynd": "ó",
			"samsetning": "stofn",
			"kennistrengur": "smáo.uh-ó"
		},
		{
			"beygingar": ["frumstig"],
			"kennistrengur": "lo-lifaður"
		}
	],
	"frumstig": {
		"sb": {
			"et": {
				"kk": ["ólifaður", "ólifaðan", "ólifuðum", "ólifaðs"],
				"kvk": ["ólifuð", "ólifaða", "ólifaðri", "ólifaðrar"],
				"hk": ["ólifað", "ólifað", "ólifuðu", "ólifaðs"]
			},
			"ft": {
				"kk": ["ólifaðir", "ólifaða", "ólifuðum", "ólifaðra"],
				"kvk": ["ólifaðar", "ólifaðar", "ólifuðum", "ólifaðra"],
				"hk": ["ólifuð", "ólifuð", "ólifuðum", "ólifaðra"]
			}
		},
		"vb": {
			"et": {
				"kk": ["ólifaði", "ólifaða", "ólifaða", "ólifaða"],
				"kvk": ["ólifaða", "ólifuðu", "ólifuðu", "ólifuðu"],
				"hk": ["ólifaða", "ólifaða", "ólifaða", "ólifaða"]
			},
			"ft": {
				"kk": ["ólifuðu", "ólifuðu", "ólifuðu", "ólifuðu"],
				"kvk": ["ólifuðu", "ólifuðu", "ólifuðu", "ólifuðu"],
				"hk": ["ólifuðu", "ólifuðu", "ólifuðu", "ólifuðu"]
			}
		}
	},
	"kennistrengur": "lo-ólifaður",
	"hash": "820c1cf2c4b6b2c8a8fa1105c4b60b92774f5e1d758dbfabe8dd46b6eead52eb"
}