{
	"orð": "Aransbur",
	"flokkur": "sérnafn",
	"undirflokkur": "kenninafn",
	"kyn": "hk",
	"samsett": [
		{
			"mynd": "Arans",
			"samsetning": "eignarfalls",
			"kennistrengur": "sérn.en-Aran-kk"
		},
		{
			"beygingar": ["et-ág", "ft-ág"],
			"kennistrengur": "no-bur-hk"
		}
	],
	"et": {
		"ág": ["Aransbur", "Aransbur", "Aransburi", "Aransburs"]
	},
	"ft": {
		"ág": ["Aransbur", "Aransbur", "Aransburum", "Aransbura"]
	},
	"kennistrengur": "sérn.kn-Aransbur-hk",
	"hash": "d645184e6c74ed307a7feb2815f481e521a8c22e3d2f3e9c3e86ff9bf9bd225d"
}