{
	"orð": "Eleonorubur",
	"flokkur": "sérnafn",
	"undirflokkur": "kenninafn",
	"kyn": "hk",
	"samsett": [
		{
			"mynd": "Eleonoru",
			"samsetning": "eignarfalls",
			"kennistrengur": "sérn.en-Eleonora-kvk"
		},
		{
			"beygingar": ["et-ág", "ft-ág"],
			"kennistrengur": "no-bur-hk"
		}
	],
	"et": {
		"ág": ["Eleonorubur", "Eleonorubur", "Eleonoruburi", "Eleonoruburs"]
	},
	"ft": {
		"ág": ["Eleonorubur", "Eleonorubur", "Eleonoruburum", "Eleonorubura"]
	},
	"kennistrengur": "sérn.kn-Eleonorubur-hk",
	"hash": "4836d5bde44ff095a43156f9fee655092ff806e722a60a65fc2d947e46934a8e"
}