{
	"orð": "Ástþrúðarbur",
	"flokkur": "sérnafn",
	"undirflokkur": "kenninafn",
	"kyn": "hk",
	"samsett": [
		{
			"mynd": "Ástþrúðar",
			"samsetning": "eignarfalls",
			"kennistrengur": "sérn.en-Ástþrúður-kvk"
		},
		{
			"beygingar": ["et-ág", "ft-ág"],
			"kennistrengur": "no-bur-hk"
		}
	],
	"et": {
		"ág": ["Ástþrúðarbur", "Ástþrúðarbur", "Ástþrúðarburi", "Ástþrúðarburs"]
	},
	"ft": {
		"ág": ["Ástþrúðarbur", "Ástþrúðarbur", "Ástþrúðarburum", "Ástþrúðarbura"]
	},
	"kennistrengur": "sérn.kn-Ástþrúðarbur-hk",
	"hash": "665d2781f7274f77f5c370531af0b9d69196b027e3cf876cb7e5680b4e291de6"
}